Metadata-Version: 2.1
Name: food-recipe-scraper
Version: 1.0.0
Summary: A python library to scrape recipe data on food automatically.
Home-page: https://datakund.com
Author: DataKund
Author-email: datakund@gmail.com
License: Apache License 2.0
Keywords: food python bot_studio scraper data recipe info web-scraping
Platform: UNKNOWN
